README
setup.py
weaver/__init__.py
weaver/exceptions.py
weaver/helpers.py
weaver/service_registry.py
weaver/tasks.py
weaver/utils.py
weaver.egg-info/PKG-INFO
weaver.egg-info/SOURCES.txt
weaver.egg-info/dependency_links.txt
weaver.egg-info/not-zip-safe
weaver.egg-info/top_level.txt
weaver/contrib/__init__.py
weaver/contrib/noah/__init__.py
weaver/contrib/noah/config.py
weaver/contrib/noah/node.py
weaver/contrib/noah/tests.py
weaver/contrib/noah/thread.py
weaver/contrib/noah/utils.py
weaver/topic/__init__.py
weaver/topic/etc.py
weaver/topic/net.py
weaver/topic/nv.py