Metadata-Version: 1.0
Name: weaver
Version: 0.1
Summary: Wrapper for Fabric
Home-page: UNKNOWN
Author: Kevin Lin
Author-email: kevinslin8@gmail.com
License: MIT
Platform: UNKNOWN
